wlkatapython.py
E4_robot/E4_UART.py
E4_robot/__init__.py
Harobot_robot/Harobot_UART.py
Harobot_robot/__init__.py
MS4220_robot/MS4220_UART.py
MS4220_robot/__init__.py
MT4_robot/MT4_UART.py
MT4_robot/__init__.py
Mirobot_robot/Mirobot_GUI.py
Mirobot_robot/Mirobot_UART.py
Mirobot_robot/__init__.py
wlkatapython-0.1.1.dist-info/LICENSE
wlkatapython-0.1.1.dist-info/METADATA
wlkatapython-0.1.1.dist-info/WHEEL
wlkatapython-0.1.1.dist-info/top_level.txt
wlkatapython-0.1.1.dist-info/RECORD
