Metadata-Version: 2.1
Name: wlkatapython
Version: 0.1.1
Summary: WLKATA-Mirobot/E4/MT4/Haro380/MS4220 Multiple robotic arm control!
Author: DSS
Classifier: Programming Language :: Python :: 3
Classifier: License :: OSI Approved :: MIT License
Classifier: Operating System :: OS Independent
License-File: LICENSE
Requires-Dist: pyserial
